simplexng/.gitignore
simplexng/__init__.py
simplexng/py.typed
simplexng/searxng_version.txt
simplexng/settings.py
simplexng/simplexng.py
simplexng/_vendor/LICENSE_NOTICE
simplexng/_vendor/SEARXNG_LICENSE
simplexng/_vendor/__init__.py
simplexng/_vendor/searx/__init__.py
simplexng/_vendor/searx/autocomplete.py
simplexng/_vendor/searx/babel_extract.py
simplexng/_vendor/searx/cache.py
simplexng/_vendor/searx/compat.py
simplexng/_vendor/searx/exceptions.py
simplexng/_vendor/searx/extended_types.py
simplexng/_vendor/searx/external_bang.py
simplexng/_vendor/searx/external_urls.py
simplexng/_vendor/searx/flaskfix.py
simplexng/_vendor/searx/limiter.py
simplexng/_vendor/searx/limiter.toml
simplexng/_vendor/searx/locales.py
simplexng/_vendor/searx/openmetrics.py
simplexng/_vendor/searx/preferences.py
simplexng/_vendor/searx/query.py
simplexng/_vendor/searx/results.py
simplexng/_vendor/searx/searxng.msg
simplexng/_vendor/searx/settings.yml
simplexng/_vendor/searx/settings_defaults.py
simplexng/_vendor/searx/settings_loader.py
simplexng/_vendor/searx/sqlitedb.py
simplexng/_vendor/searx/sxng_locales.py
simplexng/_vendor/searx/unixthreadname.py
simplexng/_vendor/searx/utils.py
simplexng/_vendor/searx/valkeydb.py
simplexng/_vendor/searx/valkeylib.py
simplexng/_vendor/searx/version.py
simplexng/_vendor/searx/version_frozen.py
simplexng/_vendor/searx/weather.py
simplexng/_vendor/searx/webadapter.py
simplexng/_vendor/searx/webapp.py
simplexng/_vendor/searx/webutils.py
simplexng/_vendor/searx/wikidata_units.py
simplexng/_vendor/searx/answerers/__init__.py
simplexng/_vendor/searx/answerers/_core.py
simplexng/_vendor/searx/answerers/random.py
simplexng/_vendor/searx/answerers/statistics.py
simplexng/_vendor/searx/botdetection/__init__.py
simplexng/_vendor/searx/botdetection/_helpers.py
simplexng/_vendor/searx/botdetection/config.py
simplexng/_vendor/searx/botdetection/http_accept.py
simplexng/_vendor/searx/botdetection/http_accept_encoding.py
simplexng-0.1.3.dist-info/METADATA
simplexng-0.1.3.dist-info/WHEEL
simplexng-0.1.3.dist-info/entry_points.txt
simplexng-0.1.3.dist-info/licenses/LICENSE
simplexng-0.1.3.dist-info/RECORD
