Metadata-Version: 2.4
Name: simplexng
Version: 0.1.3
Summary: A simple way to run SearXNG locally
Project-URL: Repository, https://github.com/jlevy/simplexng
Author-email: Joshua Levy <joshua@cal.berkeley.edu>
License-Expression: AGPL-3.0-or-later
License-File: LICENSE
Classifier: Development Status :: 4 - Beta
Classifier: Intended Audience :: Developers
Classifier: Operating System :: OS Independent
Classifier: Programming Language :: Python
Classifier: Programming Language :: Python :: 3
Classifier: Programming Language :: Python :: 3.11
Classifier: Programming Language :: Python :: 3.12
Classifier: Programming Language :: Python :: 3.13
Classifier: Typing :: Typed
Requires-Python: <4.0,>=3.11
Requires-Dist: babel==2.17.0
Requires-Dist: brotli==1.1.0
Requires-Dist: certifi==2025.7.14
Requires-Dist: clideps>=0.1.6
Requires-Dist: fasttext-predict==0.9.2.4
Requires-Dist: flask-babel==4.0.0
Requires-Dist: flask==3.1.1
Requires-Dist: httpx-socks[asyncio]==0.10.0
Requires-Dist: httpx[http2]==0.28.1
Requires-Dist: isodate==0.7.2
Requires-Dist: jinja2==3.1.6
Requires-Dist: lxml==6.0.0
Requires-Dist: markdown-it-py==3.0.0
Requires-Dist: msgspec==0.19.0
Requires-Dist: platformdirs>=4.3.8
Requires-Dist: pygments==2.19.2
Requires-Dist: python-dateutil==2.9.0.post0
Requires-Dist: pyyaml==6.0.2
Requires-Dist: rich>=14.0.0
Requires-Dist: setproctitle==1.3.6
Requires-Dist: tomli==2.2.1; python_version < '3.11'
Requires-Dist: typer-slim==0.16.0
Requires-Dist: uvloop==0.21.0
Requires-Dist: valkey==6.1.0
Requires-Dist: waitress>=3.0.2
Requires-Dist: whitenoise==6.9.0
